fh2_bailian_drc_server/__init__.py
fh2_bailian_drc_server/config/__init__.py
fh2_bailian_drc_server/config/settings.py
fh2_bailian_drc_server/core/__init__.py
fh2_bailian_drc_server/core/cache.py
fh2_bailian_drc_server/core/http_client.py
fh2_bailian_drc_server/models/__init__.py
fh2_bailian_drc_server/models/enums.py
fh2_bailian_drc_server/server.py
fh2_bailian_drc_server/services/__init__.py
fh2_bailian_drc_server/services/camera_service.py
fh2_bailian_drc_server/services/device_service.py
fh2_bailian_drc_server/services/flight_service.py
fh2_bailian_drc_server/services/panoramic_service.py
fh2_bailian_drc_server/services/poi_service.py
fh2_bailian_drc_server/services/status_service.py
fh2_bailian_drc_server/tests/__init__.py
fh2_bailian_drc_server/utils/__init__.py
fh2_bailian_drc_server/utils/helpers.py
fh2_bailian_drc_server-0.1.2.dist-info/WHEEL
fh2_bailian_drc_server-0.1.2.dist-info/entry_points.txt
fh2_bailian_drc_server-0.1.2.dist-info/METADATA
fh2_bailian_drc_server-0.1.2.dist-info/RECORD
